helix_chat/__init__.py
helix_chat/app.py
helix_chat/config.py
helix_chat/layout.tcss
helix_chat/llm_client.py
helix_chat/models.py
helix_chat/ui/components.py
helix_chat/ui/screens.py
helix_chat-0.1.0.dist-info/METADATA
helix_chat-0.1.0.dist-info/WHEEL
helix_chat-0.1.0.dist-info/entry_points.txt
helix_chat-0.1.0.dist-info/licenses/LICENSE
helix_chat-0.1.0.dist-info/RECORD
