Metadata-Version: 2.4
Name: helix_chat
Version: 0.1.0
Summary: A Terminal-native AI chat interface
Author-email: Spartan-71 <anishdabhane71@gmail.com>
License:                                  Apache License
License-File: LICENSE
Keywords: TUI,ai-chat,helix,terminal
Requires-Python: >=3.10
Requires-Dist: litellm>=1.72.2
Requires-Dist: ollama>=0.5.1
Requires-Dist: textual-dev>=1.7.0
Requires-Dist: textual>=3.3.0
Provides-Extra: dev
Requires-Dist: pre-commit; extra == 'dev'
